secbrowser/__init__.py
secbrowser/server.py
secbrowser/templates/document.html
secbrowser/templates/fundamentals.html
secbrowser/templates/index.html
secbrowser/templates/portfolio.html
secbrowser/templates/submission.html
secbrowser/templates/tables.html
secbrowser/templates/text.html
secbrowser/templates/visualize.html
secbrowser/templates/xbrl.html
secbrowser-0.0.1.dist-info/METADATA
secbrowser-0.0.1.dist-info/WHEEL
secbrowser-0.0.1.dist-info/top_level.txt
secbrowser-0.0.1.dist-info/RECORD
