Metadata-Version: 2.1
Name: secbrowser
Version: 0.0.1
Summary: A simple interface to interact with SEC filings.
Author: John Friedman
Requires-Dist: flask
Requires-Dist: datamule
